{"2026-03-02": [{"ID": 1498966, "ID\u0150PONT": "01:00", "BAJNOKS\u00c1G": "DIVISION DI HONOR", "MECCS": "Dakota - RCA", "OVER 2.5 ES\u00c9LY": "82.6%", "FAVORIT": "Nincs", "TIPP JAVASLAT": "Over 2.5 g\u00f3l | BTTS"}, {"ID": 1512968, "ID\u0150PONT": "01:00", "BAJNOKS\u00c1G": "MLS NEXT PRO", "MECCS": "Houston Dynamo FC II - Colorado Rapids II", "OVER 2.5 ES\u00c9LY": "72.3%", "FAVORIT": "VEND\u00c9G", "TIPP JAVASLAT": "Over 1.5 g\u00f3l | Vend\u00e9g csapat > 1.5 g\u00f3l"}, {"ID": 1512965, "ID\u0150PONT": "02:00", "BAJNOKS\u00c1G": "MLS NEXT PRO", "MECCS": "Ventura County - Vancouver Whitecaps II", "OVER 2.5 ES\u00c9LY": "70.6%", "FAVORIT": "Nincs", "TIPP JAVASLAT": "Over 1.5 g\u00f3l | BTTS"}, {"ID": 1512969, "ID\u0150PONT": "02:00", "BAJNOKS\u00c1G": "MLS NEXT PRO", "MECCS": "New England II - Atlanta United II", "OVER 2.5 ES\u00c9LY": "67.9%", "FAVORIT": "Nincs", "TIPP JAVASLAT": "Over 1.5 g\u00f3l | BTTS"}, {"ID": 1512971, "ID\u0150PONT": "04:00", "BAJNOKS\u00c1G": "MLS NEXT PRO", "MECCS": "Tacoma Defiance - Los Angeles FC II", "OVER 2.5 ES\u00c9LY": "75.4%", "FAVORIT": "Nincs", "TIPP JAVASLAT": "Over 2.5 g\u00f3l | BTTS"}, {"ID": 1525642, "ID\u0150PONT": "12:00", "BAJNOKS\u00c1G": "FIRST LEAGUE", "MECCS": "Ararat II - Banants II", "OVER 2.5 ES\u00c9LY": "67.9%", "FAVORIT": "Nincs", "TIPP JAVASLAT": "Over 1.5 g\u00f3l | BTTS"}, {"ID": 1525643, "ID\u0150PONT": "12:00", "BAJNOKS\u00c1G": "FIRST LEAGUE", "MECCS": "Hayq - Bentonit Ijevan", "OVER 2.5 ES\u00c9LY": "64.1%", "FAVORIT": "Nincs", "TIPP JAVASLAT": "Over 1.5 g\u00f3l"}, {"ID": 1434101, "ID\u0150PONT": "14:00", "BAJNOKS\u00c1G": "PROFESSIONAL DEVELOPMENT LEAGUE", "MECCS": "Crewe Alexandra U21 - Wigan Athletic U21", "OVER 2.5 ES\u00c9LY": "80.3%", "FAVORIT": "Nincs", "TIPP JAVASLAT": "Over 2.5 g\u00f3l | BTTS"}, {"ID": 1527522, "ID\u0150PONT": "15:00", "BAJNOKS\u00c1G": "PREMIER LEAGUE", "MECCS": "Asiagoal - Abdish-Ata", "OVER 2.5 ES\u00c9LY": "61.0%", "FAVORIT": "VEND\u00c9G", "TIPP JAVASLAT": "Over 1.5 g\u00f3l"}, {"ID": 1434108, "ID\u0150PONT": "15:30", "BAJNOKS\u00c1G": "PROFESSIONAL DEVELOPMENT LEAGUE", "MECCS": "Sheffield United U21 - Sheffield Wednesday U21", "OVER 2.5 ES\u00c9LY": "74.7%", "FAVORIT": "Nincs", "TIPP JAVASLAT": "Over 1.5 g\u00f3l | BTTS"}, {"ID": 1509062, "ID\u0150PONT": "17:00", "BAJNOKS\u00c1G": "EROVNULI LIGA", "MECCS": "Gagra - Samgurali", "OVER 2.5 ES\u00c9LY": "67.0%", "FAVORIT": "Nincs", "TIPP JAVASLAT": "Over 1.5 g\u00f3l | BTTS"}, {"ID": 1477599, "ID\u0150PONT": "18:00", "BAJNOKS\u00c1G": "I LIGA", "MECCS": "Wieczysta Krak\u00f3w - Polonia Warszawa", "OVER 2.5 ES\u00c9LY": "62.0%", "FAVORIT": "Nincs", "TIPP JAVASLAT": "Over 1.5 g\u00f3l"}, {"ID": 1521415, "ID\u0150PONT": "18:00", "BAJNOKS\u00c1G": "CONCACAF U20", "MECCS": "Sint Maarten U20 - Trinidad and Tobago U20", "OVER 2.5 ES\u00c9LY": "89.5%", "FAVORIT": "VEND\u00c9G", "TIPP JAVASLAT": "Over 2.5 g\u00f3l | Vend\u00e9g csapat > 1.5 g\u00f3l"}, {"ID": 1434535, "ID\u0150PONT": "19:00", "BAJNOKS\u00c1G": "PREMIER LEAGUE 2 DIVISION ONE", "MECCS": "Middlesbrough U21 - Birmingham City U21", "OVER 2.5 ES\u00c9LY": "73.1%", "FAVORIT": "Nincs", "TIPP JAVASLAT": "Over 1.5 g\u00f3l | BTTS"}, {"ID": 1524261, "ID\u0150PONT": "19:00", "BAJNOKS\u00c1G": "BRASILEIRO U20 A", "MECCS": "Ava\u00ed U20 - RB Bragantino U20", "OVER 2.5 ES\u00c9LY": "72.3%", "FAVORIT": "VEND\u00c9G", "TIPP JAVASLAT": "Over 1.5 g\u00f3l | Vend\u00e9g csapat > 1.5 g\u00f3l"}, {"ID": 1499033, "ID\u0150PONT": "19:45", "BAJNOKS\u00c1G": "DIVISION 1", "MECCS": "Al-Adalah - Al-Faisaly FC", "OVER 2.5 ES\u00c9LY": "75.4%", "FAVORIT": "VEND\u00c9G", "TIPP JAVASLAT": "Over 2.5 g\u00f3l | Vend\u00e9g csapat > 1.5 g\u00f3l"}, {"ID": 1434102, "ID\u0150PONT": "20:00", "BAJNOKS\u00c1G": "PROFESSIONAL DEVELOPMENT LEAGUE", "MECCS": "Swansea City U21 - Queens Park Rangers U21", "OVER 2.5 ES\u00c9LY": "62.0%", "FAVORIT": "Nincs", "TIPP JAVASLAT": "Over 1.5 g\u00f3l"}, {"ID": 1434526, "ID\u0150PONT": "20:00", "BAJNOKS\u00c1G": "PREMIER LEAGUE 2 DIVISION ONE", "MECCS": "Manchester United U21 - Chelsea U21", "OVER 2.5 ES\u00c9LY": "82.1%", "FAVORIT": "Nincs", "TIPP JAVASLAT": "Over 2.5 g\u00f3l | BTTS"}, {"ID": 1434536, "ID\u0150PONT": "20:00", "BAJNOKS\u00c1G": "PREMIER LEAGUE 2 DIVISION ONE", "MECCS": "Crystal Palace U21 - Sunderland U21", "OVER 2.5 ES\u00c9LY": "72.3%", "FAVORIT": "Nincs", "TIPP JAVASLAT": "Over 1.5 g\u00f3l | BTTS"}, {"ID": 1434539, "ID\u0150PONT": "20:00", "BAJNOKS\u00c1G": "PREMIER LEAGUE 2 DIVISION ONE", "MECCS": "West Bromwich Albion U21 - Derby County U21", "OVER 2.5 ES\u00c9LY": "68.8%", "FAVORIT": "Nincs", "TIPP JAVASLAT": "Over 1.5 g\u00f3l | BTTS"}, {"ID": 1521416, "ID\u0150PONT": "21:00", "BAJNOKS\u00c1G": "CONCACAF U20", "MECCS": "Bermuda U20 - Costa Rica U20", "OVER 2.5 ES\u00c9LY": "66.0%", "FAVORIT": "Nincs", "TIPP JAVASLAT": "Over 1.5 g\u00f3l | BTTS"}, {"ID": 1521417, "ID\u0150PONT": "22:00", "BAJNOKS\u00c1G": "CONCACAF U20", "MECCS": "Anguilla U20 - Cura\u00e7ao U20", "OVER 2.5 ES\u00c9LY": "84.3%", "FAVORIT": "VEND\u00c9G", "TIPP JAVASLAT": "Over 2.5 g\u00f3l | Vend\u00e9g csapat > 1.5 g\u00f3l"}], "2026-03-03": [{"ID": 1503468, "ID\u0150PONT": "10:30", "BAJNOKS\u00c1G": "NATIONAL LEAGUE", "MECCS": "Sagaing United - Dagon", "OVER 2.5 ES\u00c9LY": "67.9%", "FAVORIT": "Nincs", "TIPP JAVASLAT": "Over 1.5 g\u00f3l | BTTS"}, {"ID": 1525472, "ID\u0150PONT": "11:00", "BAJNOKS\u00c1G": "AFC CHAMPIONS LEAGUE", "MECCS": "Gangwon FC - Machida Zelvia", "OVER 2.5 ES\u00c9LY": "63.0%", "FAVORIT": "VEND\u00c9G", "TIPP JAVASLAT": "Over 1.5 g\u00f3l | Vend\u00e9g csapat > 1.5 g\u00f3l"}, {"ID": 1486201, "ID\u0150PONT": "12:00", "BAJNOKS\u00c1G": "CUPA", "MECCS": "Zimbru - Politehnica UTM", "OVER 2.5 ES\u00c9LY": "84.8%", "FAVORIT": "Nincs", "TIPP JAVASLAT": "Over 2.5 g\u00f3l | BTTS"}, {"ID": 1525645, "ID\u0150PONT": "12:00", "BAJNOKS\u00c1G": "FIRST LEAGUE", "MECCS": "Araks Ararat - Van II", "OVER 2.5 ES\u00c9LY": "72.3%", "FAVORIT": "Nincs", "TIPP JAVASLAT": "Over 1.5 g\u00f3l | BTTS"}, {"ID": 1525647, "ID\u0150PONT": "12:00", "BAJNOKS\u00c1G": "FIRST LEAGUE", "MECCS": "Pyunik II - Noah II", "OVER 2.5 ES\u00c9LY": "62.0%", "FAVORIT": "Nincs", "TIPP JAVASLAT": "Over 1.5 g\u00f3l"}, {"ID": 1437575, "ID\u0150PONT": "13:00", "BAJNOKS\u00c1G": "U18 PREMIER LEAGUE - NORTH", "MECCS": "Leeds United U18 - Manchester City U18", "OVER 2.5 ES\u00c9LY": "82.6%", "FAVORIT": "VEND\u00c9G", "TIPP JAVASLAT": "Over 2.5 g\u00f3l | Vend\u00e9g csapat > 1.5 g\u00f3l"}, {"ID": 1489356, "ID\u0150PONT": "13:30", "BAJNOKS\u00c1G": "T\u00dcRKIYE KUPASI", "MECCS": "\u0130stanbulspor - Boluspor", "OVER 2.5 ES\u00c9LY": "65.1%", "FAVORIT": "Nincs", "TIPP JAVASLAT": "Over 1.5 g\u00f3l | BTTS"}, {"ID": 1434103, "ID\u0150PONT": "14:00", "BAJNOKS\u00c1G": "PROFESSIONAL DEVELOPMENT LEAGUE", "MECCS": "Fleetwood Town U21 - Huddersfield Town U21", "OVER 2.5 ES\u00c9LY": "76.9%", "FAVORIT": "VEND\u00c9G", "TIPP JAVASLAT": "Over 2.5 g\u00f3l | Vend\u00e9g csapat > 1.5 g\u00f3l"}, {"ID": 1434104, "ID\u0150PONT": "14:00", "BAJNOKS\u00c1G": "PROFESSIONAL DEVELOPMENT LEAGUE", "MECCS": "Watford U21 - AFC Bournemouth U21", "OVER 2.5 ES\u00c9LY": "80.9%", "FAVORIT": "Nincs", "TIPP JAVASLAT": "Over 2.5 g\u00f3l | BTTS"}, {"ID": 1434106, "ID\u0150PONT": "14:00", "BAJNOKS\u00c1G": "PROFESSIONAL DEVELOPMENT LEAGUE", "MECCS": "Peterborough United U21 - Hull City U21", "OVER 2.5 ES\u00c9LY": "76.9%", "FAVORIT": "HAZAI", "TIPP JAVASLAT": "Over 2.5 g\u00f3l | Hazai csapat > 1.5 g\u00f3l"}, {"ID": 1441338, "ID\u0150PONT": "14:00", "BAJNOKS\u00c1G": "SECOND LEAGUE", "MECCS": "Sloga Vinica - Detonit Plachkovica", "OVER 2.5 ES\u00c9LY": "64.1%", "FAVORIT": "VEND\u00c9G", "TIPP JAVASLAT": "Over 1.5 g\u00f3l | Vend\u00e9g csapat > 1.5 g\u00f3l"}, {"ID": 1523811, "ID\u0150PONT": "14:00", "BAJNOKS\u00c1G": "WORLD CUP - WOMEN - QUALIFICATION EUROPE", "MECCS": "Montenegro W - Albania W", "OVER 2.5 ES\u00c9LY": "63.0%", "FAVORIT": "Nincs", "TIPP JAVASLAT": "Over 1.5 g\u00f3l"}, {"ID": 1403772, "ID\u0150PONT": "14:30", "BAJNOKS\u00c1G": "LIGA 1", "MECCS": "Persepam Madura Utd - Malut United", "OVER 2.5 ES\u00c9LY": "67.0%", "FAVORIT": "VEND\u00c9G", "TIPP JAVASLAT": "Over 1.5 g\u00f3l | Vend\u00e9g csapat > 1.5 g\u00f3l"}, {"ID": 1434105, "ID\u0150PONT": "14:30", "BAJNOKS\u00c1G": "PROFESSIONAL DEVELOPMENT LEAGUE", "MECCS": "Millwall U21 - Cardiff City U21", "OVER 2.5 ES\u00c9LY": "73.1%", "FAVORIT": "Nincs", "TIPP JAVASLAT": "Over 1.5 g\u00f3l | BTTS"}, {"ID": 1434107, "ID\u0150PONT": "14:30", "BAJNOKS\u00c1G": "PROFESSIONAL DEVELOPMENT LEAGUE", "MECCS": "Charlton Athletic U21 - Bristol City U21", "OVER 2.5 ES\u00c9LY": "68.8%", "FAVORIT": "Nincs", "TIPP JAVASLAT": "Over 1.5 g\u00f3l | BTTS"}, {"ID": 1437729, "ID\u0150PONT": "14:30", "BAJNOKS\u00c1G": "U18 PREMIER LEAGUE - SOUTH", "MECCS": "Chelsea U18 - Fulham U18", "OVER 2.5 ES\u00c9LY": "73.9%", "FAVORIT": "HAZAI", "TIPP JAVASLAT": "Over 1.5 g\u00f3l | Hazai csapat > 1.5 g\u00f3l"}, {"ID": 1508293, "ID\u0150PONT": "14:30", "BAJNOKS\u00c1G": "U19 DIVISIE 1", "MECCS": "Sparta Rotterdam U19 - PSV U19", "OVER 2.5 ES\u00c9LY": "73.9%", "FAVORIT": "Nincs", "TIPP JAVASLAT": "Over 1.5 g\u00f3l | BTTS"}, {"ID": 1508328, "ID\u0150PONT": "14:30", "BAJNOKS\u00c1G": "U19 DIVISIE 1", "MECCS": "PSV U19 - Sparta Rotterdam U19", "OVER 2.5 ES\u00c9LY": "73.9%", "FAVORIT": "Nincs", "TIPP JAVASLAT": "Over 1.5 g\u00f3l | BTTS"}, {"ID": 1498007, "ID\u0150PONT": "16:00", "BAJNOKS\u00c1G": "LIGA REVELA\u00c7\u00c3O U23", "MECCS": "Famalic\u00e3o U23 - Santa Clara U23", "OVER 2.5 ES\u00c9LY": "67.0%", "FAVORIT": "Nincs", "TIPP JAVASLAT": "Over 1.5 g\u00f3l | BTTS"}, {"ID": 1498008, "ID\u0150PONT": "16:00", "BAJNOKS\u00c1G": "LIGA REVELA\u00c7\u00c3O U23", "MECCS": "Sporting CP U23 - Leix\u00f5es U23", "OVER 2.5 ES\u00c9LY": "64.1%", "FAVORIT": "Nincs", "TIPP JAVASLAT": "Over 1.5 g\u00f3l | BTTS"}, {"ID": 1498076, "ID\u0150PONT": "16:00", "BAJNOKS\u00c1G": "LIGA REVELA\u00c7\u00c3O U23", "MECCS": "Portimonense U23 - Estrela U23", "OVER 2.5 ES\u00c9LY": "64.1%", "FAVORIT": "Nincs", "TIPP JAVASLAT": "Over 1.5 g\u00f3l"}, {"ID": 1523834, "ID\u0150PONT": "16:00", "BAJNOKS\u00c1G": "WORLD CUP - WOMEN - QUALIFICATION EUROPE", "MECCS": "Kazakhstan W - Armenia W", "OVER 2.5 ES\u00c9LY": "67.9%", "FAVORIT": "Nincs", "TIPP JAVASLAT": "Over 1.5 g\u00f3l | BTTS"}, {"ID": 1523830, "ID\u0150PONT": "17:00", "BAJNOKS\u00c1G": "WORLD CUP - WOMEN - QUALIFICATION EUROPE", "MECCS": "Kosovo W - Gibraltar W", "OVER 2.5 ES\u00c9LY": "77.6%", "FAVORIT": "HAZAI", "TIPP JAVASLAT": "Over 2.5 g\u00f3l | Hazai csapat > 1.5 g\u00f3l"}, {"ID": 1523816, "ID\u0150PONT": "18:00", "BAJNOKS\u00c1G": "WORLD CUP - WOMEN - QUALIFICATION EUROPE", "MECCS": "Ukraine W - England W", "OVER 2.5 ES\u00c9LY": "64.1%", "FAVORIT": "Nincs", "TIPP JAVASLAT": "Over 1.5 g\u00f3l | BTTS"}, {"ID": 1489345, "ID\u0150PONT": "18:30", "BAJNOKS\u00c1G": "T\u00dcRKIYE KUPASI", "MECCS": "Alanyaspor - Galatasaray", "OVER 2.5 ES\u00c9LY": "73.1%", "FAVORIT": "VEND\u00c9G", "TIPP JAVASLAT": "Over 1.5 g\u00f3l | Vend\u00e9g csapat > 1.5 g\u00f3l"}, {"ID": 1489348, "ID\u0150PONT": "18:30", "BAJNOKS\u00c1G": "T\u00dcRKIYE KUPASI", "MECCS": "Ba\u015fak\u015fehir - Trabzonspor", "OVER 2.5 ES\u00c9LY": "68.8%", "FAVORIT": "Nincs", "TIPP JAVASLAT": "Over 1.5 g\u00f3l | BTTS"}, {"ID": 1523810, "ID\u0150PONT": "18:30", "BAJNOKS\u00c1G": "WORLD CUP - WOMEN - QUALIFICATION EUROPE", "MECCS": "Czech Republic W - Wales W", "OVER 2.5 ES\u00c9LY": "67.0%", "FAVORIT": "Nincs", "TIPP JAVASLAT": "Over 1.5 g\u00f3l | BTTS"}, {"ID": 1394320, "ID\u0150PONT": "19:00", "BAJNOKS\u00c1G": "3. LIGA", "MECCS": "SSV Ulm 1846 - Hoffenheim II", "OVER 2.5 ES\u00c9LY": "65.1%", "FAVORIT": "Nincs", "TIPP JAVASLAT": "Over 1.5 g\u00f3l | BTTS"}, {"ID": 1407629, "ID\u0150PONT": "19:00", "BAJNOKS\u00c1G": "REGIONALLIGA - NORDOST", "MECCS": "FC Carl Zeiss Jena - Altglienicke", "OVER 2.5 ES\u00c9LY": "63.0%", "FAVORIT": "Nincs", "TIPP JAVASLAT": "Over 1.5 g\u00f3l"}, {"ID": 1523828, "ID\u0150PONT": "19:00", "BAJNOKS\u00c1G": "WORLD CUP - WOMEN - QUALIFICATION EUROPE", "MECCS": "Liechtenstein W - Lithuania W", "OVER 2.5 ES\u00c9LY": "62.0%", "FAVORIT": "VEND\u00c9G", "TIPP JAVASLAT": "Over 1.5 g\u00f3l"}, {"ID": 1528377, "ID\u0150PONT": "19:00", "BAJNOKS\u00c1G": "COPA DO BRASIL U17", "MECCS": "Fortaleza U17 - Bahia U17", "OVER 2.5 ES\u00c9LY": "67.9%", "FAVORIT": "Nincs", "TIPP JAVASLAT": "Over 1.5 g\u00f3l | BTTS"}, {"ID": 1406760, "ID\u0150PONT": "19:30", "BAJNOKS\u00c1G": "OBERLIGA - NORDOST-NORD", "MECCS": "Anker Wismar - Neustrelitz", "OVER 2.5 ES\u00c9LY": "72.3%", "FAVORIT": "Nincs", "TIPP JAVASLAT": "Over 1.5 g\u00f3l | BTTS"}, {"ID": 1523819, "ID\u0150PONT": "19:30", "BAJNOKS\u00c1G": "WORLD CUP - WOMEN - QUALIFICATION EUROPE", "MECCS": "Republic of Ireland - France W", "OVER 2.5 ES\u00c9LY": "73.1%", "FAVORIT": "Nincs", "TIPP JAVASLAT": "Over 1.5 g\u00f3l | BTTS"}, {"ID": 1523825, "ID\u0150PONT": "19:30", "BAJNOKS\u00c1G": "WORLD CUP - WOMEN - QUALIFICATION EUROPE", "MECCS": "Israel W - Belgium W", "OVER 2.5 ES\u00c9LY": "73.1%", "FAVORIT": "Nincs", "TIPP JAVASLAT": "Over 1.5 g\u00f3l | BTTS"}, {"ID": 1523826, "ID\u0150PONT": "19:30", "BAJNOKS\u00c1G": "WORLD CUP - WOMEN - QUALIFICATION EUROPE", "MECCS": "Luxembourg W - Scotland W", "OVER 2.5 ES\u00c9LY": "76.9%", "FAVORIT": "HAZAI", "TIPP JAVASLAT": "Over 2.5 g\u00f3l | Hazai csapat > 1.5 g\u00f3l"}, {"ID": 1382165, "ID\u0150PONT": "20:00", "BAJNOKS\u00c1G": "EERSTE DIVISIE", "MECCS": "Emmen - Jong Utrecht", "OVER 2.5 ES\u00c9LY": "73.9%", "FAVORIT": "Nincs", "TIPP JAVASLAT": "Over 1.5 g\u00f3l | BTTS"}, {"ID": 1382171, "ID\u0150PONT": "20:00", "BAJNOKS\u00c1G": "EERSTE DIVISIE", "MECCS": "Cambuur - Almere City FC", "OVER 2.5 ES\u00c9LY": "65.1%", "FAVORIT": "Nincs", "TIPP JAVASLAT": "Over 1.5 g\u00f3l | BTTS"}, {"ID": 1514692, "ID\u0150PONT": "20:00", "BAJNOKS\u00c1G": "LEAGUE CUP", "MECCS": "FH hafnarfjordur - Leiknir R.", "OVER 2.5 ES\u00c9LY": "71.5%", "FAVORIT": "Nincs", "TIPP JAVASLAT": "Over 1.5 g\u00f3l | BTTS"}, {"ID": 1520403, "ID\u0150PONT": "20:00", "BAJNOKS\u00c1G": "KNVB BEKER", "MECCS": "NEC Nijmegen - PSV Eindhoven", "OVER 2.5 ES\u00c9LY": "68.8%", "FAVORIT": "Nincs", "TIPP JAVASLAT": "Over 1.5 g\u00f3l | BTTS"}, {"ID": 1522559, "ID\u0150PONT": "20:00", "BAJNOKS\u00c1G": "MAGYAR KUPA", "MECCS": "Gyori ETO FC - Kecskem\u00e9ti TE", "OVER 2.5 ES\u00c9LY": "67.0%", "FAVORIT": "Nincs", "TIPP JAVASLAT": "Over 1.5 g\u00f3l | BTTS"}, {"ID": 1379252, "ID\u0150PONT": "20:30", "BAJNOKS\u00c1G": "PREMIER LEAGUE", "MECCS": "Everton - Burnley", "OVER 2.5 ES\u00c9LY": "63.0%", "FAVORIT": "Nincs", "TIPP JAVASLAT": "Over 1.5 g\u00f3l"}, {"ID": 1494560, "ID\u0150PONT": "20:30", "BAJNOKS\u00c1G": "SUPER LEAGUE", "MECCS": "FC Winterthur - Servette FC", "OVER 2.5 ES\u00c9LY": "68.8%", "FAVORIT": "Nincs", "TIPP JAVASLAT": "Over 1.5 g\u00f3l | BTTS"}, {"ID": 1499038, "ID\u0150PONT": "20:30", "BAJNOKS\u00c1G": "DIVISION 1", "MECCS": "Al Wehda Club - Al Taee", "OVER 2.5 ES\u00c9LY": "62.0%", "FAVORIT": "Nincs", "TIPP JAVASLAT": "Over 1.5 g\u00f3l"}, {"ID": 1385401, "ID\u0150PONT": "20:45", "BAJNOKS\u00c1G": "CHAMPIONSHIP", "MECCS": "Annagh United - Warrenpoint Town", "OVER 2.5 ES\u00c9LY": "61.0%", "FAVORIT": "Nincs", "TIPP JAVASLAT": "Over 1.5 g\u00f3l"}, {"ID": 1387298, "ID\u0150PONT": "20:45", "BAJNOKS\u00c1G": "LEAGUE ONE", "MECCS": "Exeter City - Burton Albion", "OVER 2.5 ES\u00c9LY": "65.1%", "FAVORIT": "Nincs", "TIPP JAVASLAT": "Over 1.5 g\u00f3l | BTTS"}, {"ID": 1387404, "ID\u0150PONT": "20:45", "BAJNOKS\u00c1G": "LEAGUE ONE", "MECCS": "Barnsley - Wycombe", "OVER 2.5 ES\u00c9LY": "65.1%", "FAVORIT": "Nincs", "TIPP JAVASLAT": "Over 1.5 g\u00f3l | BTTS"}, {"ID": 1401837, "ID\u0150PONT": "20:45", "BAJNOKS\u00c1G": "NATIONAL LEAGUE - SOUTH", "MECCS": "Torquay - Farnborough", "OVER 2.5 ES\u00c9LY": "72.3%", "FAVORIT": "Nincs", "TIPP JAVASLAT": "Over 1.5 g\u00f3l | BTTS"}, {"ID": 1402336, "ID\u0150PONT": "20:45", "BAJNOKS\u00c1G": "NATIONAL LEAGUE - NORTH", "MECCS": "Darlington 1883 - Macclesfield", "OVER 2.5 ES\u00c9LY": "70.6%", "FAVORIT": "Nincs", "TIPP JAVASLAT": "Over 1.5 g\u00f3l | BTTS"}, {"ID": 1424555, "ID\u0150PONT": "20:45", "BAJNOKS\u00c1G": "NON LEAGUE PREMIER - ISTHMIAN", "MECCS": "Wingate & Finchley - Burgess Hill Town", "OVER 2.5 ES\u00c9LY": "61.0%", "FAVORIT": "VEND\u00c9G", "TIPP JAVASLAT": "Over 1.5 g\u00f3l | Vend\u00e9g csapat > 1.5 g\u00f3l"}, {"ID": 1428369, "ID\u0150PONT": "20:45", "BAJNOKS\u00c1G": "NON LEAGUE PREMIER - SOUTHERN SOUTH", "MECCS": "Tiverton Town - Havant & Wville", "OVER 2.5 ES\u00c9LY": "61.0%", "FAVORIT": "VEND\u00c9G", "TIPP JAVASLAT": "Over 1.5 g\u00f3l | Vend\u00e9g csapat > 1.5 g\u00f3l"}, {"ID": 1443295, "ID\u0150PONT": "20:45", "BAJNOKS\u00c1G": "NON LEAGUE DIV ONE - ISTHMIAN NORTH", "MECCS": "Lowestoft Town - Walthamstow", "OVER 2.5 ES\u00c9LY": "66.0%", "FAVORIT": "VEND\u00c9G", "TIPP JAVASLAT": "Over 1.5 g\u00f3l"}, {"ID": 1521425, "ID\u0150PONT": "22:00", "BAJNOKS\u00c1G": "CONCACAF U20", "MECCS": "St Kitts and Nevis U20 - Turks and Caicos Islands U20", "OVER 2.5 ES\u00c9LY": "80.9%", "FAVORIT": "Nincs", "TIPP JAVASLAT": "Over 2.5 g\u00f3l | BTTS"}, {"ID": 1501199, "ID\u0150PONT": "23:00", "BAJNOKS\u00c1G": "CONMEBOL SUDAMERICANA", "MECCS": "Independiente Petrolero - Guabir\u00e1", "OVER 2.5 ES\u00c9LY": "78.3%", "FAVORIT": "Nincs", "TIPP JAVASLAT": "Over 2.5 g\u00f3l | BTTS"}, {"ID": 1511973, "ID\u0150PONT": "00:00", "BAJNOKS\u00c1G": "RORAIMENSE", "MECCS": "N\u00e1utico RR - Progresso", "OVER 2.5 ES\u00c9LY": "66.0%", "FAVORIT": "Nincs", "TIPP JAVASLAT": "Over 1.5 g\u00f3l | BTTS"}, {"ID": 1514404, "ID\u0150PONT": "00:00", "BAJNOKS\u00c1G": "PREMIER LEAGUE", "MECCS": "Bagatelle - Pride of Gall Hill", "OVER 2.5 ES\u00c9LY": "61.0%", "FAVORIT": "Nincs", "TIPP JAVASLAT": "Over 1.5 g\u00f3l"}, {"ID": 1521426, "ID\u0150PONT": "00:00", "BAJNOKS\u00c1G": "CONCACAF U20", "MECCS": "Belize U20 - Saint Martin U20", "OVER 2.5 ES\u00c9LY": "82.1%", "FAVORIT": "Nincs", "TIPP JAVASLAT": "Over 2.5 g\u00f3l | BTTS"}]}