{"date": "2026-04-29", "tips": [{"fixture_id": 1535171, "model_p": 0.7603, "ev": 2.8014, "odds": {"over15": 5.0, "over25": 1.93}, "fair_odds": {"over15": 1.32, "over25": 1.93}, "lambda": 2.75}, {"fixture_id": 1535281, "model_p": 0.7421, "ev": 1.5603, "odds": {"over15": 3.45, "over25": 2.02}, "fair_odds": {"over15": 1.35, "over25": 2.02}, "lambda": 2.65}, {"fixture_id": 1535179, "model_p": 0.8009, "ev": 3.4047, "odds": {"over15": 5.5, "over25": 1.73}, "fair_odds": {"over15": 1.25, "over25": 1.73}, "lambda": 3.0}, {"fixture_id": 1535182, "model_p": 0.7023, "ev": 3.0382, "odds": {"over15": 5.75, "over25": 2.26}, "fair_odds": {"over15": 1.42, "over25": 2.26}, "lambda": 2.45}, {"fixture_id": 1540252, "model_p": 0.9281, "ev": null, "odds": {"over15": null, "over25": 1.25}, "fair_odds": {"over15": 1.08, "over25": 1.25}, "lambda": 4.3}, {"fixture_id": 1540846, "model_p": 0.7603, "ev": 2.4212, "odds": {"over15": 4.5, "over25": 1.93}, "fair_odds": {"over15": 1.32, "over25": 1.93}, "lambda": 2.75}, {"fixture_id": 1535180, "model_p": 0.7023, "ev": 1.4931, "odds": {"over15": 3.55, "over25": 2.26}, "fair_odds": {"over15": 1.42, "over25": 2.26}, "lambda": 2.45}, {"fixture_id": 1535271, "model_p": 0.7127, "ev": 2.3853, "odds": {"over15": 4.75, "over25": 2.19}, "fair_odds": {"over15": 1.4, "over25": 2.19}, "lambda": 2.5}, {"fixture_id": 1535279, "model_p": 0.7228, "ev": 3.1562, "odds": {"over15": 5.75, "over25": 2.13}, "fair_odds": {"over15": 1.38, "over25": 2.13}, "lambda": 2.55}, {"fixture_id": 1540855, "model_p": 0.6454, "ev": 2.3885, "odds": {"over15": 5.25, "over25": 2.65}, "fair_odds": {"over15": 1.55, "over25": 2.65}, "lambda": 2.2}, {"fixture_id": 1504769, "model_p": 0.6805, "ev": 2.913, "odds": {"over15": 5.75, "over25": 2.4}, "fair_odds": {"over15": 1.47, "over25": 2.4}, "lambda": 2.35}, {"fixture_id": 1504770, "model_p": 0.7603, "ev": 2.4212, "odds": {"over15": 4.5, "over25": 1.93}, "fair_odds": {"over15": 1.32, "over25": 1.93}, "lambda": 2.75}, {"fixture_id": 1516750, "model_p": 0.7023, "ev": 1.1771, "odds": {"over15": 3.1, "over25": 2.26}, "fair_odds": {"over15": 1.42, "over25": 2.26}, "lambda": 2.45}, {"fixture_id": 1504771, "model_p": 0.7127, "ev": 1.5301, "odds": {"over15": 3.55, "over25": 2.19}, "fair_odds": {"over15": 1.4, "over25": 2.19}, "lambda": 2.5}, {"fixture_id": 1504772, "model_p": 0.7689, "ev": 2.0757, "odds": {"over15": 4.0, "over25": 1.88}, "fair_odds": {"over15": 1.3, "over25": 1.88}, "lambda": 2.8}, {"fixture_id": 1504773, "model_p": 0.7326, "ev": 3.0294, "odds": {"over15": 5.5, "over25": 2.08}, "fair_odds": {"over15": 1.36, "over25": 2.08}, "lambda": 2.6}, {"fixture_id": 1516751, "model_p": 0.6916, "ev": 1.7662, "odds": {"over15": 4.0, "over25": 2.32}, "fair_odds": {"over15": 1.45, "over25": 2.32}, "lambda": 2.4}, {"fixture_id": 1516752, "model_p": 0.7933, "ev": 0.6658, "odds": {"over15": 2.1, "over25": 1.77}, "fair_odds": {"over15": 1.26, "over25": 1.77}, "lambda": 2.95}, {"fixture_id": 1516753, "model_p": 0.6916, "ev": 1.4205, "odds": {"over15": 3.5, "over25": 2.32}, "fair_odds": {"over15": 1.45, "over25": 2.32}, "lambda": 2.4}, {"fixture_id": 1516754, "model_p": 0.7603, "ev": 0.2544, "odds": {"over15": 1.65, "over25": 1.93}, "fair_odds": {"over15": 1.32, "over25": 1.93}, "lambda": 2.75}, {"fixture_id": 1516755, "model_p": 0.8641, "ev": 1.1171, "odds": {"over15": 2.45, "over25": 1.47}, "fair_odds": {"over15": 1.16, "over25": 1.47}, "lambda": 3.5}, {"fixture_id": 1516756, "model_p": 0.7603, "ev": 1.4709, "odds": {"over15": 3.25, "over25": 1.93}, "fair_odds": {"over15": 1.32, "over25": 1.93}, "lambda": 2.75}, {"fixture_id": 1516757, "model_p": 0.7127, "ev": 0.9956, "odds": {"over15": 2.8, "over25": 2.19}, "fair_odds": {"over15": 1.4, "over25": 2.19}, "lambda": 2.5}, {"fixture_id": 1516759, "model_p": 0.7854, "ev": 1.5526, "odds": {"over15": 3.25, "over25": 1.8}, "fair_odds": {"over15": 1.27, "over25": 1.8}, "lambda": 2.9}, {"fixture_id": 1516760, "model_p": 0.8222, "ev": null, "odds": {"over15": null, "over25": 1.64}, "fair_odds": {"over15": 1.22, "over25": 1.64}, "lambda": 3.15}, {"fixture_id": 1516765, "model_p": 0.7854, "ev": null, "odds": {"over15": null, "over25": 1.8}, "fair_odds": {"over15": 1.27, "over25": 1.8}, "lambda": 2.9}, {"fixture_id": 1504774, "model_p": 0.7854, "ev": 2.927, "odds": {"over15": 5.0, "over25": 1.8}, "fair_odds": {"over15": 1.27, "over25": 1.8}, "lambda": 2.9}, {"fixture_id": 1504775, "model_p": 0.7689, "ev": 4.3825, "odds": {"over15": 7.0, "over25": 1.88}, "fair_odds": {"over15": 1.3, "over25": 1.88}, "lambda": 2.8}, {"fixture_id": 1504776, "model_p": 0.8288, "ev": 2.7296, "odds": {"over15": 4.5, "over25": 1.61}, "fair_odds": {"over15": 1.21, "over25": 1.61}, "lambda": 3.2}, {"fixture_id": 1504777, "model_p": 0.7127, "ev": 2.9199, "odds": {"over15": 5.5, "over25": 2.19}, "fair_odds": {"over15": 1.4, "over25": 2.19}, "lambda": 2.5}, {"fixture_id": 1531668, "model_p": 0.9794, "ev": null, "odds": {"over15": null, "over25": 1.08}, "fair_odds": {"over15": 1.02, "over25": 1.08}, "lambda": 5.8}, {"fixture_id": 1532688, "model_p": 0.7023, "ev": null, "odds": {"over15": null, "over25": 2.26}, "fair_odds": {"over15": 1.42, "over25": 2.26}, "lambda": 2.45}, {"fixture_id": 1536781, "model_p": 0.6805, "ev": null, "odds": {"over15": null, "over25": 2.4}, "fair_odds": {"over15": 1.47, "over25": 2.4}, "lambda": 2.35}, {"fixture_id": 1403827, "model_p": 0.8791, "ev": 0.5561, "odds": {"over15": 1.77, "over25": 1.42}, "fair_odds": {"over15": 1.14, "over25": 1.42}, "lambda": 3.65}, {"fixture_id": 1403828, "model_p": 0.7854, "ev": 1.0578, "odds": {"over15": 2.62, "over25": 1.8}, "fair_odds": {"over15": 1.27, "over25": 1.8}, "lambda": 2.9}, {"fixture_id": 1516768, "model_p": 0.6916, "ev": null, "odds": {"over15": null, "over25": 2.32}, "fair_odds": {"over15": 1.45, "over25": 2.32}, "lambda": 2.4}, {"fixture_id": 1516769, "model_p": 0.8791, "ev": null, "odds": {"over15": null, "over25": 1.42}, "fair_odds": {"over15": 1.14, "over25": 1.42}, "lambda": 3.65}, {"fixture_id": 1523703, "model_p": 0.8153, "ev": null, "odds": {"over15": null, "over25": 1.67}, "fair_odds": {"over15": 1.23, "over25": 1.67}, "lambda": 3.1}, {"fixture_id": 1534688, "model_p": 0.946, "ev": null, "odds": {"over15": null, "over25": 1.19}, "fair_odds": {"over15": 1.06, "over25": 1.19}, "lambda": 4.65}, {"fixture_id": 1540347, "model_p": 0.8352, "ev": null, "odds": {"over15": null, "over25": 1.59}, "fair_odds": {"over15": 1.2, "over25": 1.59}, "lambda": 3.25}, {"fixture_id": 1481968, "model_p": 0.9251, "ev": null, "odds": {"over15": null, "over25": 1.26}, "fair_odds": {"over15": 1.08, "over25": 1.26}, "lambda": 4.25}, {"fixture_id": 1502288, "model_p": 0.8968, "ev": null, "odds": {"over15": null, "over25": 1.35}, "fair_odds": {"over15": 1.12, "over25": 1.35}, "lambda": 3.85}, {"fixture_id": 1502289, "model_p": 0.912, "ev": null, "odds": {"over15": null, "over25": 1.3}, "fair_odds": {"over15": 1.1, "over25": 1.3}, "lambda": 4.05}, {"fixture_id": 1536776, "model_p": 0.8009, "ev": null, "odds": {"over15": null, "over25": 1.73}, "fair_odds": {"over15": 1.25, "over25": 1.73}, "lambda": 3.0}, {"fixture_id": 1540344, "model_p": 0.7023, "ev": null, "odds": {"over15": null, "over25": 2.26}, "fair_odds": {"over15": 1.42, "over25": 2.26}, "lambda": 2.45}, {"fixture_id": 1541025, "model_p": 0.6204, "ev": null, "odds": {"over15": null, "over25": 2.85}, "fair_odds": {"over15": 1.61, "over25": 2.85}, "lambda": 2.1}, {"fixture_id": 1466966, "model_p": 0.7023, "ev": null, "odds": {"over15": null, "over25": 2.26}, "fair_odds": {"over15": 1.42, "over25": 2.26}, "lambda": 2.45}, {"fixture_id": 1491261, "model_p": 0.7513, "ev": 0.3524, "odds": {"over15": 1.8, "over25": 1.97}, "fair_odds": {"over15": 1.33, "over25": 1.97}, "lambda": 2.7}, {"fixture_id": 1531455, "model_p": 0.8222, "ev": null, "odds": {"over15": null, "over25": 1.64}, "fair_odds": {"over15": 1.22, "over25": 1.64}, "lambda": 3.15}, {"fixture_id": 1531456, "model_p": 0.8153, "ev": null, "odds": {"over15": null, "over25": 1.67}, "fair_odds": {"over15": 1.23, "over25": 1.67}, "lambda": 3.1}, {"fixture_id": 1531457, "model_p": 0.7854, "ev": null, "odds": {"over15": null, "over25": 1.8}, "fair_odds": {"over15": 1.27, "over25": 1.8}, "lambda": 2.9}, {"fixture_id": 1531458, "model_p": 0.7689, "ev": null, "odds": {"over15": null, "over25": 1.88}, "fair_odds": {"over15": 1.3, "over25": 1.88}, "lambda": 2.8}, {"fixture_id": 1531459, "model_p": 0.7513, "ev": null, "odds": {"over15": null, "over25": 1.97}, "fair_odds": {"over15": 1.33, "over25": 1.97}, "lambda": 2.7}, {"fixture_id": 1531461, "model_p": 0.7023, "ev": null, "odds": {"over15": null, "over25": 2.26}, "fair_odds": {"over15": 1.42, "over25": 2.26}, "lambda": 2.45}, {"fixture_id": 1531462, "model_p": 0.7228, "ev": null, "odds": {"over15": null, "over25": 2.13}, "fair_odds": {"over15": 1.38, "over25": 2.13}, "lambda": 2.55}, {"fixture_id": 1531463, "model_p": 0.6916, "ev": null, "odds": {"over15": null, "over25": 2.32}, "fair_odds": {"over15": 1.45, "over25": 2.32}, "lambda": 2.4}, {"fixture_id": 1531664, "model_p": 0.9803, "ev": null, "odds": {"over15": null, "over25": 1.07}, "fair_odds": {"over15": 1.02, "over25": 1.07}, "lambda": 5.85}, {"fixture_id": 1535362, "model_p": 0.6805, "ev": null, "odds": {"over15": null, "over25": 2.4}, "fair_odds": {"over15": 1.47, "over25": 2.4}, "lambda": 2.35}, {"fixture_id": 1535364, "model_p": 0.7603, "ev": null, "odds": {"over15": null, "over25": 1.93}, "fair_odds": {"over15": 1.32, "over25": 1.93}, "lambda": 2.75}, {"fixture_id": 1536779, "model_p": 0.7421, "ev": null, "odds": {"over15": null, "over25": 2.02}, "fair_odds": {"over15": 1.35, "over25": 2.02}, "lambda": 2.65}, {"fixture_id": 1540343, "model_p": 0.7127, "ev": null, "odds": {"over15": null, "over25": 2.19}, "fair_odds": {"over15": 1.4, "over25": 2.19}, "lambda": 2.5}, {"fixture_id": 1541577, "model_p": 0.9672, "ev": null, "odds": {"over15": null, "over25": 1.12}, "fair_odds": {"over15": 1.03, "over25": 1.12}, "lambda": 5.25}, {"fixture_id": 1541582, "model_p": 0.9596, "ev": null, "odds": {"over15": null, "over25": 1.14}, "fair_odds": {"over15": 1.04, "over25": 1.14}, "lambda": 5.0}, {"fixture_id": 1437637, "model_p": 0.9309, "ev": null, "odds": {"over15": null, "over25": 1.24}, "fair_odds": {"over15": 1.07, "over25": 1.24}, "lambda": 4.35}, {"fixture_id": 1481965, "model_p": 0.8838, "ev": null, "odds": {"over15": null, "over25": 1.4}, "fair_odds": {"over15": 1.13, "over25": 1.4}, "lambda": 3.7}, {"fixture_id": 1541576, "model_p": 0.9008, "ev": null, "odds": {"over15": null, "over25": 1.34}, "fair_odds": {"over15": 1.11, "over25": 1.34}, "lambda": 3.9}, {"fixture_id": 1437813, "model_p": 0.912, "ev": null, "odds": {"over15": null, "over25": 1.3}, "fair_odds": {"over15": 1.1, "over25": 1.3}, "lambda": 4.05}, {"fixture_id": 1491250, "model_p": 0.8414, "ev": 0.1948, "odds": {"over15": 1.42, "over25": 1.56}, "fair_odds": {"over15": 1.19, "over25": 1.56}, "lambda": 3.3}, {"fixture_id": 1507331, "model_p": 0.7689, "ev": null, "odds": {"over15": null, "over25": 1.88}, "fair_odds": {"over15": 1.3, "over25": 1.88}, "lambda": 2.8}, {"fixture_id": 1507332, "model_p": 0.9084, "ev": null, "odds": {"over15": null, "over25": 1.31}, "fair_odds": {"over15": 1.1, "over25": 1.31}, "lambda": 4.0}, {"fixture_id": 1507333, "model_p": 0.7689, "ev": null, "odds": {"over15": null, "over25": 1.88}, "fair_odds": {"over15": 1.3, "over25": 1.88}, "lambda": 2.8}, {"fixture_id": 1507334, "model_p": 0.6805, "ev": null, "odds": {"over15": null, "over25": 2.4}, "fair_odds": {"over15": 1.47, "over25": 2.4}, "lambda": 2.35}, {"fixture_id": 1507336, "model_p": 0.8288, "ev": null, "odds": {"over15": null, "over25": 1.61}, "fair_odds": {"over15": 1.21, "over25": 1.61}, "lambda": 3.2}, {"fixture_id": 1507337, "model_p": 0.8743, "ev": null, "odds": {"over15": null, "over25": 1.43}, "fair_odds": {"over15": 1.14, "over25": 1.43}, "lambda": 3.6}, {"fixture_id": 1541578, "model_p": 0.9503, "ev": null, "odds": {"over15": null, "over25": 1.17}, "fair_odds": {"over15": 1.05, "over25": 1.17}, "lambda": 4.75}, {"fixture_id": 1416174, "model_p": 0.6805, "ev": null, "odds": {"over15": null, "over25": 2.4}, "fair_odds": {"over15": 1.47, "over25": 2.4}, "lambda": 2.35}, {"fixture_id": 1512076, "model_p": 0.6916, "ev": null, "odds": {"over15": null, "over25": 2.32}, "fair_odds": {"over15": 1.45, "over25": 2.32}, "lambda": 2.4}, {"fixture_id": 1512881, "model_p": 0.7513, "ev": null, "odds": {"over15": null, "over25": 1.97}, "fair_odds": {"over15": 1.33, "over25": 1.97}, "lambda": 2.7}, {"fixture_id": 1512887, "model_p": 0.7326, "ev": null, "odds": {"over15": null, "over25": 2.08}, "fair_odds": {"over15": 1.36, "over25": 2.08}, "lambda": 2.6}, {"fixture_id": 1540345, "model_p": 0.7773, "ev": null, "odds": {"over15": null, "over25": 1.84}, "fair_odds": {"over15": 1.29, "over25": 1.84}, "lambda": 2.85}, {"fixture_id": 1542097, "model_p": 0.8288, "ev": null, "odds": {"over15": null, "over25": 1.61}, "fair_odds": {"over15": 1.21, "over25": 1.61}, "lambda": 3.2}, {"fixture_id": 1542363, "model_p": 0.7513, "ev": null, "odds": {"over15": null, "over25": 1.97}, "fair_odds": {"over15": 1.33, "over25": 1.97}, "lambda": 2.7}, {"fixture_id": 1542365, "model_p": 0.6805, "ev": 1.1096, "odds": {"over15": 3.1, "over25": 2.4}, "fair_odds": {"over15": 1.47, "over25": 2.4}, "lambda": 2.35}, {"fixture_id": 1542366, "model_p": 0.7326, "ev": null, "odds": {"over15": null, "over25": 2.08}, "fair_odds": {"over15": 1.36, "over25": 2.08}, "lambda": 2.6}, {"fixture_id": 1542626, "model_p": 0.7421, "ev": null, "odds": {"over15": null, "over25": 2.02}, "fair_odds": {"over15": 1.35, "over25": 2.02}, "lambda": 2.65}, {"fixture_id": 1542628, "model_p": 0.8587, "ev": null, "odds": {"over15": null, "over25": 1.49}, "fair_odds": {"over15": 1.16, "over25": 1.49}, "lambda": 3.45}, {"fixture_id": 1542629, "model_p": 0.7127, "ev": null, "odds": {"over15": null, "over25": 2.19}, "fair_odds": {"over15": 1.4, "over25": 2.19}, "lambda": 2.5}, {"fixture_id": 1541581, "model_p": 0.9309, "ev": null, "odds": {"over15": null, "over25": 1.24}, "fair_odds": {"over15": 1.07, "over25": 1.24}, "lambda": 4.35}, {"fixture_id": 1471999, "model_p": 0.7421, "ev": null, "odds": {"over15": null, "over25": 2.02}, "fair_odds": {"over15": 1.35, "over25": 2.02}, "lambda": 2.65}, {"fixture_id": 1461279, "model_p": 0.6916, "ev": null, "odds": {"over15": null, "over25": 2.32}, "fair_odds": {"over15": 1.45, "over25": 2.32}, "lambda": 2.4}, {"fixture_id": 1495051, "model_p": 0.8222, "ev": null, "odds": {"over15": null, "over25": 1.64}, "fair_odds": {"over15": 1.22, "over25": 1.64}, "lambda": 3.15}, {"fixture_id": 1495052, "model_p": 0.8082, "ev": null, "odds": {"over15": null, "over25": 1.7}, "fair_odds": {"over15": 1.24, "over25": 1.7}, "lambda": 3.05}, {"fixture_id": 1495053, "model_p": 0.7933, "ev": null, "odds": {"over15": null, "over25": 1.77}, "fair_odds": {"over15": 1.26, "over25": 1.77}, "lambda": 2.95}, {"fixture_id": 1495055, "model_p": 0.8082, "ev": null, "odds": {"over15": null, "over25": 1.7}, "fair_odds": {"over15": 1.24, "over25": 1.7}, "lambda": 3.05}, {"fixture_id": 1495056, "model_p": 0.8532, "ev": null, "odds": {"over15": null, "over25": 1.51}, "fair_odds": {"over15": 1.17, "over25": 1.51}, "lambda": 3.4}, {"fixture_id": 1495057, "model_p": 0.8082, "ev": null, "odds": {"over15": null, "over25": 1.7}, "fair_odds": {"over15": 1.24, "over25": 1.7}, "lambda": 3.05}, {"fixture_id": 1495059, "model_p": 0.6575, "ev": null, "odds": {"over15": null, "over25": 2.56}, "fair_odds": {"over15": 1.52, "over25": 2.56}, "lambda": 2.25}, {"fixture_id": 1507330, "model_p": 0.7933, "ev": null, "odds": {"over15": null, "over25": 1.77}, "fair_odds": {"over15": 1.26, "over25": 1.77}, "lambda": 2.95}, {"fixture_id": 1516047, "model_p": 0.7228, "ev": null, "odds": {"over15": null, "over25": 2.13}, "fair_odds": {"over15": 1.38, "over25": 2.13}, "lambda": 2.55}, {"fixture_id": 1527535, "model_p": 0.7854, "ev": null, "odds": {"over15": null, "over25": 1.8}, "fair_odds": {"over15": 1.27, "over25": 1.8}, "lambda": 2.9}, {"fixture_id": 1487472, "model_p": 0.7854, "ev": null, "odds": {"over15": null, "over25": 1.8}, "fair_odds": {"over15": 1.27, "over25": 1.8}, "lambda": 2.9}, {"fixture_id": 1487473, "model_p": 0.7933, "ev": null, "odds": {"over15": null, "over25": 1.77}, "fair_odds": {"over15": 1.26, "over25": 1.77}, "lambda": 2.95}, {"fixture_id": 1487475, "model_p": 0.8153, "ev": null, "odds": {"over15": null, "over25": 1.67}, "fair_odds": {"over15": 1.23, "over25": 1.67}, "lambda": 3.1}, {"fixture_id": 1487476, "model_p": 0.8288, "ev": null, "odds": {"over15": null, "over25": 1.61}, "fair_odds": {"over15": 1.21, "over25": 1.61}, "lambda": 3.2}, {"fixture_id": 1487478, "model_p": 0.8352, "ev": null, "odds": {"over15": null, "over25": 1.59}, "fair_odds": {"over15": 1.2, "over25": 1.59}, "lambda": 3.25}, {"fixture_id": 1487479, "model_p": 0.8532, "ev": null, "odds": {"over15": null, "over25": 1.51}, "fair_odds": {"over15": 1.17, "over25": 1.51}, "lambda": 3.4}, {"fixture_id": 1487480, "model_p": 0.8414, "ev": null, "odds": {"over15": null, "over25": 1.56}, "fair_odds": {"over15": 1.19, "over25": 1.56}, "lambda": 3.3}, {"fixture_id": 1512885, "model_p": 0.7127, "ev": null, "odds": {"over15": null, "over25": 2.19}, "fair_odds": {"over15": 1.4, "over25": 2.19}, "lambda": 2.5}, {"fixture_id": 1515630, "model_p": 0.7127, "ev": null, "odds": {"over15": null, "over25": 2.19}, "fair_odds": {"over15": 1.4, "over25": 2.19}, "lambda": 2.5}, {"fixture_id": 1539633, "model_p": 0.9047, "ev": null, "odds": {"over15": null, "over25": 1.33}, "fair_odds": {"over15": 1.11, "over25": 1.33}, "lambda": 3.95}, {"fixture_id": 1539634, "model_p": 0.6805, "ev": null, "odds": {"over15": null, "over25": 2.4}, "fair_odds": {"over15": 1.47, "over25": 2.4}, "lambda": 2.35}, {"fixture_id": 1542210, "model_p": 0.8641, "ev": null, "odds": {"over15": null, "over25": 1.47}, "fair_odds": {"over15": 1.16, "over25": 1.47}, "lambda": 3.5}, {"fixture_id": 1542885, "model_p": 0.7773, "ev": null, "odds": {"over15": null, "over25": 1.84}, "fair_odds": {"over15": 1.29, "over25": 1.84}, "lambda": 2.85}, {"fixture_id": 1542887, "model_p": 0.7127, "ev": null, "odds": {"over15": null, "over25": 2.19}, "fair_odds": {"over15": 1.4, "over25": 2.19}, "lambda": 2.5}, {"fixture_id": 1411016, "model_p": 0.8791, "ev": null, "odds": {"over15": null, "over25": 1.42}, "fair_odds": {"over15": 1.14, "over25": 1.42}, "lambda": 3.65}, {"fixture_id": 1512884, "model_p": 0.7689, "ev": null, "odds": {"over15": null, "over25": 1.88}, "fair_odds": {"over15": 1.3, "over25": 1.88}, "lambda": 2.8}, {"fixture_id": 1537137, "model_p": 0.7421, "ev": 0.7811, "odds": {"over15": 2.4, "over25": 2.02}, "fair_odds": {"over15": 1.35, "over25": 2.02}, "lambda": 2.65}, {"fixture_id": 1540084, "model_p": 0.8082, "ev": null, "odds": {"over15": null, "over25": 1.7}, "fair_odds": {"over15": 1.24, "over25": 1.7}, "lambda": 3.05}, {"fixture_id": 1541835, "model_p": 0.6916, "ev": null, "odds": {"over15": null, "over25": 2.32}, "fair_odds": {"over15": 1.45, "over25": 2.32}, "lambda": 2.4}, {"fixture_id": 1542205, "model_p": 0.9723, "ev": null, "odds": {"over15": null, "over25": 1.1}, "fair_odds": {"over15": 1.03, "over25": 1.1}, "lambda": 5.45}, {"fixture_id": 1542209, "model_p": 0.9847, "ev": null, "odds": {"over15": null, "over25": 1.06}, "fair_odds": {"over15": 1.02, "over25": 1.06}, "lambda": 6.15}, {"fixture_id": 1542216, "model_p": 0.7228, "ev": null, "odds": {"over15": null, "over25": 2.13}, "fair_odds": {"over15": 1.38, "over25": 2.13}, "lambda": 2.55}, {"fixture_id": 1543064, "model_p": 0.7773, "ev": null, "odds": {"over15": null, "over25": 1.84}, "fair_odds": {"over15": 1.29, "over25": 1.84}, "lambda": 2.85}, {"fixture_id": 1542208, "model_p": 0.9047, "ev": null, "odds": {"over15": null, "over25": 1.33}, "fair_odds": {"over15": 1.11, "over25": 1.33}, "lambda": 3.95}, {"fixture_id": 1538425, "model_p": 0.8352, "ev": 6.0993, "odds": {"over15": 8.5, "over25": 1.59}, "fair_odds": {"over15": 1.2, "over25": 1.59}, "lambda": 3.25}, {"fixture_id": 1388270, "model_p": 0.7689, "ev": null, "odds": {"over15": null, "over25": 1.88}, "fair_odds": {"over15": 1.3, "over25": 1.88}, "lambda": 2.8}, {"fixture_id": 1466965, "model_p": 0.8414, "ev": null, "odds": {"over15": null, "over25": 1.56}, "fair_odds": {"over15": 1.19, "over25": 1.56}, "lambda": 3.3}, {"fixture_id": 1542202, "model_p": 0.9084, "ev": null, "odds": {"over15": null, "over25": 1.31}, "fair_odds": {"over15": 1.1, "over25": 1.31}, "lambda": 4.0}, {"fixture_id": 1401333, "model_p": 0.8082, "ev": -0.014, "odds": {"over15": 1.22, "over25": 1.7}, "fair_odds": {"over15": 1.24, "over25": 1.7}, "lambda": 3.05}, {"fixture_id": 1436181, "model_p": 0.7854, "ev": 0.8457, "odds": {"over15": 2.35, "over25": 1.8}, "fair_odds": {"over15": 1.27, "over25": 1.8}, "lambda": 2.9}, {"fixture_id": 1487474, "model_p": 0.8414, "ev": null, "odds": {"over15": null, "over25": 1.56}, "fair_odds": {"over15": 1.19, "over25": 1.56}, "lambda": 3.3}, {"fixture_id": 1487477, "model_p": 0.8352, "ev": null, "odds": {"over15": null, "over25": 1.59}, "fair_odds": {"over15": 1.2, "over25": 1.59}, "lambda": 3.25}, {"fixture_id": 1495379, "model_p": 0.8587, "ev": null, "odds": {"over15": null, "over25": 1.49}, "fair_odds": {"over15": 1.16, "over25": 1.49}, "lambda": 3.45}, {"fixture_id": 1495380, "model_p": 0.7127, "ev": null, "odds": {"over15": null, "over25": 2.19}, "fair_odds": {"over15": 1.4, "over25": 2.19}, "lambda": 2.5}, {"fixture_id": 1495722, "model_p": 0.7603, "ev": 2.6113, "odds": {"over15": 4.75, "over25": 1.93}, "fair_odds": {"over15": 1.32, "over25": 1.93}, "lambda": 2.75}, {"fixture_id": 1525434, "model_p": 0.7228, "ev": 0.7709, "odds": {"over15": 2.45, "over25": 2.13}, "fair_odds": {"over15": 1.38, "over25": 2.13}, "lambda": 2.55}, {"fixture_id": 1535357, "model_p": 0.7854, "ev": 2.927, "odds": {"over15": 5.0, "over25": 1.8}, "fair_odds": {"over15": 1.27, "over25": 1.8}, "lambda": 2.9}, {"fixture_id": 1535359, "model_p": 0.6916, "ev": null, "odds": {"over15": null, "over25": 2.32}, "fair_odds": {"over15": 1.45, "over25": 2.32}, "lambda": 2.4}, {"fixture_id": 1540682, "model_p": 0.7933, "ev": 3.3629, "odds": {"over15": 5.5, "over25": 1.77}, "fair_odds": {"over15": 1.26, "over25": 1.77}, "lambda": 2.95}, {"fixture_id": 1540683, "model_p": 0.8641, "ev": 2.7416, "odds": {"over15": 4.33, "over25": 1.47}, "fair_odds": {"over15": 1.16, "over25": 1.47}, "lambda": 3.5}, {"fixture_id": 1541579, "model_p": 0.8926, "ev": null, "odds": {"over15": null, "over25": 1.37}, "fair_odds": {"over15": 1.12, "over25": 1.37}, "lambda": 3.8}, {"fixture_id": 1542218, "model_p": 0.9047, "ev": null, "odds": {"over15": null, "over25": 1.33}, "fair_odds": {"over15": 1.11, "over25": 1.33}, "lambda": 3.95}, {"fixture_id": 1543065, "model_p": 0.8082, "ev": null, "odds": {"over15": null, "over25": 1.7}, "fair_odds": {"over15": 1.24, "over25": 1.7}, "lambda": 3.05}, {"fixture_id": 1436176, "model_p": 0.7603, "ev": 1.699, "odds": {"over15": 3.55, "over25": 1.93}, "fair_odds": {"over15": 1.32, "over25": 1.93}, "lambda": 2.75}, {"fixture_id": 1542206, "model_p": 0.8641, "ev": null, "odds": {"over15": null, "over25": 1.47}, "fair_odds": {"over15": 1.16, "over25": 1.47}, "lambda": 3.5}, {"fixture_id": 1407384, "model_p": 0.8153, "ev": null, "odds": {"over15": null, "over25": 1.67}, "fair_odds": {"over15": 1.23, "over25": 1.67}, "lambda": 3.1}, {"fixture_id": 1512353, "model_p": 0.7689, "ev": null, "odds": {"over15": null, "over25": 1.88}, "fair_odds": {"over15": 1.3, "over25": 1.88}, "lambda": 2.8}, {"fixture_id": 1540709, "model_p": 0.7228, "ev": 1.8912, "odds": {"over15": 4.0, "over25": 2.13}, "fair_odds": {"over15": 1.38, "over25": 2.13}, "lambda": 2.55}, {"fixture_id": 1542201, "model_p": 0.7513, "ev": null, "odds": {"over15": null, "over25": 1.97}, "fair_odds": {"over15": 1.33, "over25": 1.97}, "lambda": 2.7}, {"fixture_id": 1542219, "model_p": 0.8743, "ev": null, "odds": {"over15": null, "over25": 1.43}, "fair_odds": {"over15": 1.14, "over25": 1.43}, "lambda": 3.6}, {"fixture_id": 1542766, "model_p": 0.8288, "ev": 1.8179, "odds": {"over15": 3.4, "over25": 1.61}, "fair_odds": {"over15": 1.21, "over25": 1.61}, "lambda": 3.2}, {"fixture_id": 1407053, "model_p": 0.8222, "ev": null, "odds": {"over15": null, "over25": 1.64}, "fair_odds": {"over15": 1.22, "over25": 1.64}, "lambda": 3.15}, {"fixture_id": 1407376, "model_p": 0.8838, "ev": null, "odds": {"over15": null, "over25": 1.4}, "fair_odds": {"over15": 1.13, "over25": 1.4}, "lambda": 3.7}, {"fixture_id": 1407738, "model_p": 0.8883, "ev": null, "odds": {"over15": null, "over25": 1.38}, "fair_odds": {"over15": 1.13, "over25": 1.38}, "lambda": 3.75}, {"fixture_id": 1409883, "model_p": 0.7689, "ev": null, "odds": {"over15": null, "over25": 1.88}, "fair_odds": {"over15": 1.3, "over25": 1.88}, "lambda": 2.8}, {"fixture_id": 1412809, "model_p": 0.7228, "ev": null, "odds": {"over15": null, "over25": 2.13}, "fair_odds": {"over15": 1.38, "over25": 2.13}, "lambda": 2.55}, {"fixture_id": 1414294, "model_p": 0.9628, "ev": null, "odds": {"over15": null, "over25": 1.13}, "fair_odds": {"over15": 1.04, "over25": 1.13}, "lambda": 5.1}, {"fixture_id": 1418715, "model_p": 0.8883, "ev": 0.1548, "odds": {"over15": 1.3, "over25": 1.38}, "fair_odds": {"over15": 1.13, "over25": 1.38}, "lambda": 3.75}, {"fixture_id": 1421646, "model_p": 0.7513, "ev": null, "odds": {"over15": null, "over25": 1.97}, "fair_odds": {"over15": 1.33, "over25": 1.97}, "lambda": 2.7}, {"fixture_id": 1464129, "model_p": 0.8641, "ev": null, "odds": {"over15": null, "over25": 1.47}, "fair_odds": {"over15": 1.16, "over25": 1.47}, "lambda": 3.5}, {"fixture_id": 1494724, "model_p": 0.7603, "ev": 3.3716, "odds": {"over15": 5.75, "over25": 1.93}, "fair_odds": {"over15": 1.32, "over25": 1.93}, "lambda": 2.75}, {"fixture_id": 1516324, "model_p": 0.7326, "ev": null, "odds": {"over15": null, "over25": 2.08}, "fair_odds": {"over15": 1.36, "over25": 2.08}, "lambda": 2.6}, {"fixture_id": 1533621, "model_p": 0.5221, "ev": 3.438, "odds": {"over15": 8.5, "over25": 3.91}, "fair_odds": {"over15": 1.92, "over25": 3.91}, "lambda": 1.75}, {"fixture_id": 1533857, "model_p": 0.8641, "ev": null, "odds": {"over15": null, "over25": 1.47}, "fair_odds": {"over15": 1.16, "over25": 1.47}, "lambda": 3.5}, {"fixture_id": 1534132, "model_p": 0.7023, "ev": null, "odds": {"over15": null, "over25": 2.26}, "fair_odds": {"over15": 1.42, "over25": 2.26}, "lambda": 2.45}, {"fixture_id": 1541836, "model_p": 0.8414, "ev": null, "odds": {"over15": null, "over25": 1.56}, "fair_odds": {"over15": 1.19, "over25": 1.56}, "lambda": 3.3}, {"fixture_id": 1541936, "model_p": 0.7127, "ev": 0.012, "odds": {"over15": 1.42, "over25": 2.19}, "fair_odds": {"over15": 1.4, "over25": 2.19}, "lambda": 2.5}, {"fixture_id": 1543066, "model_p": 0.7228, "ev": null, "odds": {"over15": null, "over25": 2.13}, "fair_odds": {"over15": 1.38, "over25": 2.13}, "lambda": 2.55}, {"fixture_id": 1408265, "model_p": 0.8743, "ev": null, "odds": {"over15": null, "over25": 1.43}, "fair_odds": {"over15": 1.14, "over25": 1.43}, "lambda": 3.6}, {"fixture_id": 1409384, "model_p": 0.8968, "ev": null, "odds": {"over15": null, "over25": 1.35}, "fair_odds": {"over15": 1.12, "over25": 1.35}, "lambda": 3.85}, {"fixture_id": 1409921, "model_p": 0.7513, "ev": null, "odds": {"over15": null, "over25": 1.97}, "fair_odds": {"over15": 1.33, "over25": 1.97}, "lambda": 2.7}, {"fixture_id": 1506574, "model_p": 0.9008, "ev": null, "odds": {"over15": null, "over25": 1.34}, "fair_odds": {"over15": 1.11, "over25": 1.34}, "lambda": 3.9}, {"fixture_id": 1540790, "model_p": 0.8082, "ev": null, "odds": {"over15": null, "over25": 1.7}, "fair_odds": {"over15": 1.24, "over25": 1.7}, "lambda": 3.05}, {"fixture_id": 1540791, "model_p": 0.8968, "ev": null, "odds": {"over15": null, "over25": 1.35}, "fair_odds": {"over15": 1.12, "over25": 1.35}, "lambda": 3.85}, {"fixture_id": 1540913, "model_p": 0.8288, "ev": null, "odds": {"over15": null, "over25": 1.61}, "fair_odds": {"over15": 1.21, "over25": 1.61}, "lambda": 3.2}, {"fixture_id": 1412784, "model_p": 0.8352, "ev": null, "odds": {"over15": null, "over25": 1.59}, "fair_odds": {"over15": 1.2, "over25": 1.59}, "lambda": 3.25}, {"fixture_id": 1417274, "model_p": 0.7854, "ev": 10.7811, "odds": {"over15": 15.0, "over25": 1.8}, "fair_odds": {"over15": 1.27, "over25": 1.8}, "lambda": 2.9}, {"fixture_id": 1436179, "model_p": 0.8352, "ev": 2.9672, "odds": {"over15": 4.75, "over25": 1.59}, "fair_odds": {"over15": 1.2, "over25": 1.59}, "lambda": 3.25}, {"fixture_id": 1512346, "model_p": 0.7127, "ev": null, "odds": {"over15": null, "over25": 2.19}, "fair_odds": {"over15": 1.4, "over25": 2.19}, "lambda": 2.5}, {"fixture_id": 1512348, "model_p": 0.7773, "ev": null, "odds": {"over15": null, "over25": 1.84}, "fair_odds": {"over15": 1.29, "over25": 1.84}, "lambda": 2.85}, {"fixture_id": 1512358, "model_p": 0.8587, "ev": null, "odds": {"over15": null, "over25": 1.49}, "fair_odds": {"over15": 1.16, "over25": 1.49}, "lambda": 3.45}, {"fixture_id": 1512362, "model_p": 0.7228, "ev": null, "odds": {"over15": null, "over25": 2.13}, "fair_odds": {"over15": 1.38, "over25": 2.13}, "lambda": 2.55}, {"fixture_id": 1526103, "model_p": 0.8926, "ev": null, "odds": {"over15": null, "over25": 1.37}, "fair_odds": {"over15": 1.12, "over25": 1.37}, "lambda": 3.8}, {"fixture_id": 1526105, "model_p": 0.7603, "ev": null, "odds": {"over15": null, "over25": 1.93}, "fair_odds": {"over15": 1.32, "over25": 1.93}, "lambda": 2.75}, {"fixture_id": 1526108, "model_p": 0.8009, "ev": null, "odds": {"over15": null, "over25": 1.73}, "fair_odds": {"over15": 1.25, "over25": 1.73}, "lambda": 3.0}, {"fixture_id": 1526110, "model_p": 0.8641, "ev": null, "odds": {"over15": null, "over25": 1.47}, "fair_odds": {"over15": 1.16, "over25": 1.47}, "lambda": 3.5}, {"fixture_id": 1526111, "model_p": 0.8414, "ev": null, "odds": {"over15": null, "over25": 1.56}, "fair_odds": {"over15": 1.19, "over25": 1.56}, "lambda": 3.3}, {"fixture_id": 1538523, "model_p": 0.8009, "ev": null, "odds": {"over15": null, "over25": 1.73}, "fair_odds": {"over15": 1.25, "over25": 1.73}, "lambda": 3.0}, {"fixture_id": 1538525, "model_p": 0.6805, "ev": null, "odds": {"over15": null, "over25": 2.4}, "fair_odds": {"over15": 1.47, "over25": 2.4}, "lambda": 2.35}, {"fixture_id": 1538526, "model_p": 0.7326, "ev": null, "odds": {"over15": null, "over25": 2.08}, "fair_odds": {"over15": 1.36, "over25": 2.08}, "lambda": 2.6}, {"fixture_id": 1540174, "model_p": 0.7127, "ev": null, "odds": {"over15": null, "over25": 2.19}, "fair_odds": {"over15": 1.4, "over25": 2.19}, "lambda": 2.5}, {"fixture_id": 1540883, "model_p": 0.8153, "ev": null, "odds": {"over15": null, "over25": 1.67}, "fair_odds": {"over15": 1.23, "over25": 1.67}, "lambda": 3.1}, {"fixture_id": 1542203, "model_p": 0.9579, "ev": null, "odds": {"over15": null, "over25": 1.15}, "fair_odds": {"over15": 1.04, "over25": 1.15}, "lambda": 4.95}, {"fixture_id": 1542214, "model_p": 0.8641, "ev": null, "odds": {"over15": null, "over25": 1.47}, "fair_odds": {"over15": 1.16, "over25": 1.47}, "lambda": 3.5}, {"fixture_id": 1542791, "model_p": 0.8838, "ev": 1.0327, "odds": {"over15": 2.3, "over25": 1.4}, "fair_odds": {"over15": 1.13, "over25": 1.4}, "lambda": 3.7}, {"fixture_id": 1542793, "model_p": 0.7513, "ev": 0.9159, "odds": {"over15": 2.55, "over25": 1.97}, "fair_odds": {"over15": 1.33, "over25": 1.97}, "lambda": 2.7}, {"fixture_id": 1542795, "model_p": 0.8222, "ev": 1.1541, "odds": {"over15": 2.62, "over25": 1.64}, "fair_odds": {"over15": 1.22, "over25": 1.64}, "lambda": 3.15}, {"fixture_id": 1542796, "model_p": 0.7689, "ev": null, "odds": {"over15": null, "over25": 1.88}, "fair_odds": {"over15": 1.3, "over25": 1.88}, "lambda": 2.8}, {"fixture_id": 1542797, "model_p": 0.8082, "ev": null, "odds": {"over15": null, "over25": 1.7}, "fair_odds": {"over15": 1.24, "over25": 1.7}, "lambda": 3.05}, {"fixture_id": 1542864, "model_p": 0.7773, "ev": null, "odds": {"over15": null, "over25": 1.84}, "fair_odds": {"over15": 1.29, "over25": 1.84}, "lambda": 2.85}, {"fixture_id": 1543037, "model_p": 0.8474, "ev": null, "odds": {"over15": null, "over25": 1.54}, "fair_odds": {"over15": 1.18, "over25": 1.54}, "lambda": 3.35}, {"fixture_id": 1543038, "model_p": 0.7421, "ev": null, "odds": {"over15": null, "over25": 2.02}, "fair_odds": {"over15": 1.35, "over25": 2.02}, "lambda": 2.65}, {"fixture_id": 1543039, "model_p": 0.8153, "ev": null, "odds": {"over15": null, "over25": 1.67}, "fair_odds": {"over15": 1.23, "over25": 1.67}, "lambda": 3.1}, {"fixture_id": 1543040, "model_p": 0.8474, "ev": null, "odds": {"over15": null, "over25": 1.54}, "fair_odds": {"over15": 1.18, "over25": 1.54}, "lambda": 3.35}, {"fixture_id": 1526107, "model_p": 0.7421, "ev": null, "odds": {"over15": null, "over25": 2.02}, "fair_odds": {"over15": 1.35, "over25": 2.02}, "lambda": 2.65}, {"fixture_id": 1540842, "model_p": 0.8009, "ev": 3.4047, "odds": {"over15": 5.5, "over25": 1.73}, "fair_odds": {"over15": 1.25, "over25": 1.73}, "lambda": 3.0}, {"fixture_id": 1396469, "model_p": 0.7513, "ev": 0.3299, "odds": {"over15": 1.77, "over25": 1.97}, "fair_odds": {"over15": 1.33, "over25": 1.97}, "lambda": 2.7}, {"fixture_id": 1506107, "model_p": 0.7421, "ev": null, "odds": {"over15": null, "over25": 2.02}, "fair_odds": {"over15": 1.35, "over25": 2.02}, "lambda": 2.65}, {"fixture_id": 1506108, "model_p": 0.6916, "ev": null, "odds": {"over15": null, "over25": 2.32}, "fair_odds": {"over15": 1.45, "over25": 2.32}, "lambda": 2.4}, {"fixture_id": 1506111, "model_p": 0.7513, "ev": null, "odds": {"over15": null, "over25": 1.97}, "fair_odds": {"over15": 1.33, "over25": 1.97}, "lambda": 2.7}, {"fixture_id": 1506112, "model_p": 0.6331, "ev": null, "odds": {"over15": null, "over25": 2.75}, "fair_odds": {"over15": 1.58, "over25": 2.75}, "lambda": 2.15}, {"fixture_id": 1506113, "model_p": 0.7228, "ev": 2.7948, "odds": {"over15": 5.25, "over25": 2.13}, "fair_odds": {"over15": 1.38, "over25": 2.13}, "lambda": 2.55}, {"fixture_id": 1506114, "model_p": 0.7326, "ev": null, "odds": {"over15": null, "over25": 2.08}, "fair_odds": {"over15": 1.36, "over25": 2.08}, "lambda": 2.6}, {"fixture_id": 1506116, "model_p": 0.6916, "ev": null, "odds": {"over15": null, "over25": 2.32}, "fair_odds": {"over15": 1.45, "over25": 2.32}, "lambda": 2.4}, {"fixture_id": 1535122, "model_p": 0.7326, "ev": null, "odds": {"over15": null, "over25": 2.08}, "fair_odds": {"over15": 1.36, "over25": 2.08}, "lambda": 2.6}, {"fixture_id": 1535123, "model_p": 0.7326, "ev": null, "odds": {"over15": null, "over25": 2.08}, "fair_odds": {"over15": 1.36, "over25": 2.08}, "lambda": 2.6}, {"fixture_id": 1535125, "model_p": 0.7127, "ev": null, "odds": {"over15": null, "over25": 2.19}, "fair_odds": {"over15": 1.4, "over25": 2.19}, "lambda": 2.5}, {"fixture_id": 1535126, "model_p": 0.8153, "ev": null, "odds": {"over15": null, "over25": 1.67}, "fair_odds": {"over15": 1.23, "over25": 1.67}, "lambda": 3.1}, {"fixture_id": 1526511, "model_p": 0.7773, "ev": null, "odds": {"over15": null, "over25": 1.84}, "fair_odds": {"over15": 1.29, "over25": 1.84}, "lambda": 2.85}, {"fixture_id": 1542371, "model_p": 0.6805, "ev": 1.8582, "odds": {"over15": 4.2, "over25": 2.4}, "fair_odds": {"over15": 1.47, "over25": 2.4}, "lambda": 2.35}, {"fixture_id": 1526112, "model_p": 0.8414, "ev": null, "odds": {"over15": null, "over25": 1.56}, "fair_odds": {"over15": 1.19, "over25": 1.56}, "lambda": 3.3}, {"fixture_id": 1526515, "model_p": 0.6691, "ev": null, "odds": {"over15": null, "over25": 2.48}, "fair_odds": {"over15": 1.49, "over25": 2.48}, "lambda": 2.3}, {"fixture_id": 1542898, "model_p": 0.7127, "ev": null, "odds": {"over15": null, "over25": 2.19}, "fair_odds": {"over15": 1.4, "over25": 2.19}, "lambda": 2.5}, {"fixture_id": 1535178, "model_p": 0.6916, "ev": 2.2849, "odds": {"over15": 4.75, "over25": 2.32}, "fair_odds": {"over15": 1.45, "over25": 2.32}, "lambda": 2.4}, {"fixture_id": 1535277, "model_p": 0.8288, "ev": 0.8648, "odds": {"over15": 2.25, "over25": 1.61}, "fair_odds": {"over15": 1.21, "over25": 1.61}, "lambda": 3.2}, {"fixture_id": 1535278, "model_p": 0.5068, "ev": null, "odds": {"over15": null, "over25": 4.12}, "fair_odds": {"over15": 1.97, "over25": 4.12}, "lambda": 1.7}, {"fixture_id": 1537292, "model_p": 0.8352, "ev": null, "odds": {"over15": null, "over25": 1.59}, "fair_odds": {"over15": 1.2, "over25": 1.59}, "lambda": 3.25}, {"fixture_id": 1537293, "model_p": 0.7854, "ev": null, "odds": {"over15": null, "over25": 1.8}, "fair_odds": {"over15": 1.27, "over25": 1.8}, "lambda": 2.9}, {"fixture_id": 1537294, "model_p": 0.7603, "ev": null, "odds": {"over15": null, "over25": 1.93}, "fair_odds": {"over15": 1.32, "over25": 1.93}, "lambda": 2.75}, {"fixture_id": 1537296, "model_p": 0.6805, "ev": null, "odds": {"over15": null, "over25": 2.4}, "fair_odds": {"over15": 1.47, "over25": 2.4}, "lambda": 2.35}, {"fixture_id": 1537297, "model_p": 0.7421, "ev": null, "odds": {"over15": null, "over25": 2.02}, "fair_odds": {"over15": 1.35, "over25": 2.02}, "lambda": 2.65}, {"fixture_id": 1537358, "model_p": 0.6805, "ev": null, "odds": {"over15": null, "over25": 2.4}, "fair_odds": {"over15": 1.47, "over25": 2.4}, "lambda": 2.35}, {"fixture_id": 1537359, "model_p": 0.7603, "ev": null, "odds": {"over15": null, "over25": 1.93}, "fair_odds": {"over15": 1.32, "over25": 1.93}, "lambda": 2.75}, {"fixture_id": 1537360, "model_p": 0.8222, "ev": null, "odds": {"over15": null, "over25": 1.64}, "fair_odds": {"over15": 1.22, "over25": 1.64}, "lambda": 3.15}, {"fixture_id": 1541129, "model_p": 0.7023, "ev": 1.9496, "odds": {"over15": 4.2, "over25": 2.26}, "fair_odds": {"over15": 1.42, "over25": 2.26}, "lambda": 2.45}, {"fixture_id": 1542902, "model_p": 0.6805, "ev": null, "odds": {"over15": null, "over25": 2.4}, "fair_odds": {"over15": 1.47, "over25": 2.4}, "lambda": 2.35}, {"fixture_id": 1541949, "model_p": 0.7421, "ev": null, "odds": {"over15": null, "over25": 2.02}, "fair_odds": {"over15": 1.35, "over25": 2.02}, "lambda": 2.65}, {"fixture_id": 1508401, "model_p": 0.7127, "ev": 1.9934, "odds": {"over15": 4.2, "over25": 2.19}, "fair_odds": {"over15": 1.4, "over25": 2.19}, "lambda": 2.5}, {"fixture_id": 1540854, "model_p": 0.8641, "ev": 2.8885, "odds": {"over15": 4.5, "over25": 1.47}, "fair_odds": {"over15": 1.16, "over25": 1.47}, "lambda": 3.5}, {"fixture_id": 1542652, "model_p": 0.6805, "ev": null, "odds": {"over15": null, "over25": 2.4}, "fair_odds": {"over15": 1.47, "over25": 2.4}, "lambda": 2.35}, {"fixture_id": 1540851, "model_p": 0.7513, "ev": 5.0107, "odds": {"over15": 8.0, "over25": 1.97}, "fair_odds": {"over15": 1.33, "over25": 1.97}, "lambda": 2.7}, {"fixture_id": 1540853, "model_p": 0.9188, "ev": 3.3644, "odds": {"over15": 4.75, "over25": 1.28}, "fair_odds": {"over15": 1.09, "over25": 1.28}, "lambda": 4.15}]}